cuttpy/__init__.py
cuttpy/cuttpy.py
cuttpy/response.py
cuttpy-1.1.1.dist-info/LICENSE
cuttpy-1.1.1.dist-info/METADATA
cuttpy-1.1.1.dist-info/WHEEL
cuttpy-1.1.1.dist-info/top_level.txt
cuttpy-1.1.1.dist-info/RECORD
