Metadata-Version: 2.1
Name: cuttpy
Version: 1.1.1
Summary: Wrapper for the cutt.ly URL shortener API.
Home-page: https://github.com/IAmThe2ndHuman/cuttpy
Author: IAmThe2ndHuman
License: MIT
Platform: UNKNOWN
Classifier: Programming Language :: Python :: 3
Classifier: License :: OSI Approved :: MIT License
Requires-Python: >=3.6
Requires-Dist: requests
